sequentialized_barnard_tests/__init__.py
sequentialized_barnard_tests/auto.py
sequentialized_barnard_tests/base.py
sequentialized_barnard_tests/batch.py
sequentialized_barnard_tests/lai.py
sequentialized_barnard_tests/savi.py
sequentialized_barnard_tests/step.py
sequentialized_barnard_tests/data/lai_calibration_data.npy
sequentialized_barnard_tests/policies/n_max_200_alpha_0.05_shape_parameter_0.0_pnorm_False/policy_compressed.pkl
sequentialized_barnard_tests/policies/n_max_500_alpha_0.05_shape_parameter_0.0_pnorm_False/policy_compressed.pkl
sequentialized_barnard_tests/scripts/synthesize_general_step_policy.py
sequentialized_barnard_tests/tools/__init__.py
sequentialized_barnard_tests/tools/plotting.py
sequentialized_barnard_tests/utils/__init__.py
sequentialized_barnard_tests/utils/utils_general.py
sequentialized_barnard_tests/utils/utils_lai.py
sequentialized_barnard_tests/utils/utils_step.py
sequentialized_barnard_tests-0.0.5.dist-info/licenses/LICENSE
sequentialized_barnard_tests-0.0.5.dist-info/METADATA
sequentialized_barnard_tests-0.0.5.dist-info/WHEEL
sequentialized_barnard_tests-0.0.5.dist-info/top_level.txt
sequentialized_barnard_tests-0.0.5.dist-info/RECORD
