Metadata-Version: 2.4
Name: sequentialized_barnard_tests
Version: 0.0.5
Summary: Sequential statistical hypothesis testing for two-by-two contingency tables.
License: MIT
License-File: LICENSE
Requires-Dist: binomial_cis
Requires-Dist: matplotlib
Requires-Dist: numpy>=1.20
Requires-Dist: pytest
Requires-Dist: scipy
Requires-Dist: tqdm
Dynamic: license
Dynamic: license-file
Dynamic: requires-dist
Dynamic: summary
